math_ops_131/__init__.py
math_ops_131/calculator.py
math_ops_131-1.5.2.dist-info/METADATA
math_ops_131-1.5.2.dist-info/WHEEL
math_ops_131-1.5.2.dist-info/top_level.txt
math_ops_131-1.5.2.dist-info/RECORD
