Metadata-Version: 2.1
Name: math-ops-131
Version: 1.5.2
Summary: A Python package for basic mathematical operations.
Home-page: https://github.com/AspiringPianist/math_ops_131
Author: Unnath Chittimalla
Author-email: unnath.chittimalla@iiitb.ac.in
License: MIT License
Platform: UNKNOWN
Classifier: Programming Language :: Python :: 3
Classifier: License :: OSI Approved :: MIT License
Classifier: Operating System :: OS Independent
